hpctoolkit_dataframe/__init__.py
hpctoolkit_dataframe/_version.py
hpctoolkit_dataframe/hpctoolkit_dataframe.py
hpctoolkit_dataframe-0.3.0.dist-info/LICENSE
hpctoolkit_dataframe-0.3.0.dist-info/METADATA
hpctoolkit_dataframe-0.3.0.dist-info/NOTICE
hpctoolkit_dataframe-0.3.0.dist-info/WHEEL
hpctoolkit_dataframe-0.3.0.dist-info/top_level.txt
hpctoolkit_dataframe-0.3.0.dist-info/RECORD
